mousebit/__init__.py
mousebit/image.py
mousebit/structured.py
mousebit/text.py
MouseBit-0.0.2.dist-info/LICENSE.txt
MouseBit-0.0.2.dist-info/METADATA
MouseBit-0.0.2.dist-info/WHEEL
MouseBit-0.0.2.dist-info/top_level.txt
MouseBit-0.0.2.dist-info/RECORD
