Metadata-Version: 2.1
Name: MouseBit
Version: 0.0.2
Summary: An easy to use PyTorch utility for easy DataLoader creation.
Home-page: https://github.com/krypticmouse/MouseBit
Author: Herumb Shandilya
Author-email: herumbshandilya123@gmail.com
License: UNKNOWN
Platform: UNKNOWN
Classifier: Programming Language :: Python :: 3
Classifier: License :: OSI Approved :: MIT License
Classifier: Operating System :: OS Independent
Requires-Python: >=3.6
